Anime/Anime.py
Anime/__init__.py
Anime/img_anime.py
Anime/video_anime.py
webUI/__init__.py
webUI/webUI.py
Gao_Anime-5.28.dist-info/METADATA
Gao_Anime-5.28.dist-info/WHEEL
Gao_Anime-5.28.dist-info/top_level.txt
Gao_Anime-5.28.dist-info/RECORD
