Metadata-Version: 2.1
Name: Gao-Anime
Version: 5.28
Summary: AI Head
Home-page: https://github.com/CuteCar384/Gao_Anime
Author: Huang
Author-email: 1664625666@qq.com
License: MIT
Classifier: License :: OSI Approved :: MIT License
Classifier: Programming Language :: Python
Classifier: Programming Language :: Python :: 3
Classifier: Programming Language :: Python :: 3.8
Classifier: Programming Language :: Python :: Implementation :: CPython
Classifier: Programming Language :: Python :: Implementation :: PyPy
Requires-Python: >=3.8
Requires-Dist: aiofiles ==23.2.1
Requires-Dist: aiohttp ==3.9.1
Requires-Dist: aiosignal ==1.3.1
Requires-Dist: altair ==5.2.0
Requires-Dist: annotated-types ==0.6.0
Requires-Dist: anyio ==3.7.1
Requires-Dist: argon2-cffi ==23.1.0
Requires-Dist: argon2-cffi-bindings ==21.2.0
Requires-Dist: arrow ==1.2.3
Requires-Dist: astor ==0.8.1
Requires-Dist: async-lru ==2.0.4
Requires-Dist: async-timeout ==4.0.3
Requires-Dist: attrs ==23.1.0
Requires-Dist: gradio
Requires-Dist: Babel ==2.12.1
Requires-Dist: bce-python-sdk ==0.8.97
Requires-Dist: beautifulsoup4 ==4.12.2
Requires-Dist: bleach ==6.0.0
Requires-Dist: blinker ==1.7.0
Requires-Dist: certifi ==2023.11.17
Requires-Dist: cffi ==1.15.1
Requires-Dist: charset-normalizer ==3.3.2
Requires-Dist: click ==8.1.7
Requires-Dist: colorama ==0.4.6
Requires-Dist: colorlog ==6.8.0
Requires-Dist: contourpy ==1.1.0
Requires-Dist: cycler ==0.11.0
Requires-Dist: datasets ==2.15.0
Requires-Dist: decorator ==5.1.1
Requires-Dist: defusedxml ==0.7.1
Requires-Dist: dill ==0.3.4
Requires-Dist: easydict ==1.11
Requires-Dist: exceptiongroup ==1.1.3
Requires-Dist: fastapi ==0.105.0
Requires-Dist: ffmpy ==0.3.1
Requires-Dist: filelock ==3.13.1
Requires-Dist: Flask ==3.0.0
Requires-Dist: flask-babel ==4.0.0
Requires-Dist: fonttools ==4.42.1
Requires-Dist: fqdn ==1.5.1
Requires-Dist: frozenlist ==1.4.0
Requires-Dist: fsspec ==2023.10.0
Requires-Dist: future ==0.18.3
Requires-Dist: Gao-Anime ==5.28
Requires-Dist: gradio ==4.9.0
Requires-Dist: gradio-client ==0.7.2
Requires-Dist: h11 ==0.14.0
Requires-Dist: httpcore ==1.0.2
Requires-Dist: httpx ==0.25.2
Requires-Dist: huggingface-hub ==0.19.4
Requires-Dist: idna ==3.6
Requires-Dist: importlib-metadata ==7.0.0
Requires-Dist: importlib-resources ==6.0.1
Requires-Dist: ipywidgets ==8.1.0
Requires-Dist: isoduration ==20.11.0
Requires-Dist: itsdangerous ==2.1.2
Requires-Dist: jieba ==0.42.1
Requires-Dist: Jinja2 ==3.1.2
Requires-Dist: joblib ==1.3.2
Requires-Dist: jsonpointer ==2.4
Requires-Dist: jsonschema ==4.19.0
Requires-Dist: jsonschema-specifications ==2023.7.1
Requires-Dist: jupyter ==1.0.0
Requires-Dist: jupyter-console ==6.6.3
Requires-Dist: jupyter-events ==0.7.0
Requires-Dist: jupyter-lsp ==2.2.0
Requires-Dist: jupyter-server ==2.7.3
Requires-Dist: jupyter-server-terminals ==0.4.4
Requires-Dist: jupyterlab ==4.0.5
Requires-Dist: jupyterlab-pygments ==0.2.2
Requires-Dist: jupyterlab-widgets ==3.0.8
Requires-Dist: jupyterlab-server ==2.25.0
Requires-Dist: kiwisolver ==1.4.5
Requires-Dist: markdown-it-py ==3.0.0
Requires-Dist: MarkupSafe ==2.1.3
Requires-Dist: matplotlib ==3.7.4
Requires-Dist: mdurl ==0.1.2
Requires-Dist: mistune ==3.0.1
Requires-Dist: multidict ==6.0.4
Requires-Dist: multiprocess ==0.70.12.2
Requires-Dist: nbclient ==0.8.0
Requires-Dist: nbconvert ==7.8.0
Requires-Dist: nbformat ==5.9.2
Requires-Dist: notebook ==7.0.3
Requires-Dist: notebook-shim ==0.2.3
Requires-Dist: numpy
Requires-Dist: onnx ==1.15.0
Requires-Dist: opencv-python ==4.8.1.78
Requires-Dist: opt-einsum ==3.3.0
Requires-Dist: orjson ==3.9.10
Requires-Dist: packaging ==23.2
Requires-Dist: paddle2onnx ==1.0.6
Requires-Dist: paddlefsl ==1.1.0
Requires-Dist: paddlehub ==2.4.0
Requires-Dist: paddlenlp ==2.6.1
Requires-Dist: paddlepaddle ==2.5.2
Requires-Dist: pandas ==2.0.3
Requires-Dist: Pillow ==10.1.0
Requires-Dist: pkgutil-resolve-name ==1.3.10
Requires-Dist: protobuf ==3.20.2
Requires-Dist: psutil ==5.9.6
Requires-Dist: pyarrow ==14.0.1
Requires-Dist: pyarrow-hotfix ==0.6
Requires-Dist: pycryptodome ==3.19.0
Requires-Dist: pydantic ==2.5.2
Requires-Dist: pydantic-core ==2.14.5
Requires-Dist: pydub ==0.25.1
Requires-Dist: Pygments ==2.17.2
Requires-Dist: pyparsing ==3.1.1
Requires-Dist: python-dateutil ==2.8.2
Requires-Dist: python-multipart ==0.0.6
Requires-Dist: pytz ==2023.3.post1
Requires-Dist: PyYAML ==6.0.1
Requires-Dist: pyzmq ==25.1.2
Requires-Dist: qtconsole ==5.4.4
Requires-Dist: rarfile ==4.1
Requires-Dist: referencing ==0.30.2
Requires-Dist: requests ==2.31.0
Requires-Dist: rich ==13.7.0
Requires-Dist: rpds-py ==0.13.2
Requires-Dist: safetensors ==0.4.1
Requires-Dist: scikit-learn ==1.3.2
Requires-Dist: scipy ==1.10.1
Requires-Dist: semantic-version ==2.10.0
Requires-Dist: sentencepiece ==0.1.99
Requires-Dist: seqeval ==1.2.2
Requires-Dist: shellingham ==1.5.4
Requires-Dist: six ==1.16.0
Requires-Dist: sniffio ==1.3.0
Requires-Dist: starlette ==0.27.0
Requires-Dist: terminado ==0.17.1
Requires-Dist: threadpoolctl ==3.2.0
Requires-Dist: tomlkit ==0.12.0
Requires-Dist: toolz ==0.12.0
Requires-Dist: tqdm ==4.66.1
Requires-Dist: typer ==0.9.0
Requires-Dist: typing-extensions ==4.9.0
Requires-Dist: tzdata ==2023.3
Requires-Dist: urllib3 ==2.1.0
Requires-Dist: uvicorn ==0.24.0.post1
Requires-Dist: visualdl ==2.5.3
Requires-Dist: websockets ==11.0.3
Requires-Dist: Werkzeug ==3.0.1
Requires-Dist: xxhash ==3.4.1
Requires-Dist: yarl ==1.9.4
Requires-Dist: zipp ==3.17.0
